target_postgres/__init__.py
target_postgres/db_sync.py
splitgraph_pipelinewise_target_postgres-2.1.0.dist-info/LICENSE
splitgraph_pipelinewise_target_postgres-2.1.0.dist-info/METADATA
splitgraph_pipelinewise_target_postgres-2.1.0.dist-info/WHEEL
splitgraph_pipelinewise_target_postgres-2.1.0.dist-info/entry_points.txt
splitgraph_pipelinewise_target_postgres-2.1.0.dist-info/top_level.txt
splitgraph_pipelinewise_target_postgres-2.1.0.dist-info/RECORD
