Metadata-Version: 2.1
Name: splitgraph-pipelinewise-target-postgres
Version: 2.1.0
Summary: Singer.io target for loading data to PostgreSQL - PipelineWise compatible
Home-page: https://github.com/transferwise/pipelinewise-target-postgres
Author: TransferWise
License: UNKNOWN
Platform: UNKNOWN
Classifier: License :: OSI Approved :: Apache Software License
Classifier: Programming Language :: Python :: 3 :: Only
Requires-Dist: psycopg2-binary (>=2.8.5)
Requires-Dist: inflection (>=0.3.1)
Requires-Dist: joblib (>=0.13.2)
Provides-Extra: test
Requires-Dist: nose (==1.3.7) ; extra == 'test'
Requires-Dist: mock (==3.0.5) ; extra == 'test'
Requires-Dist: pylint (==2.4.4) ; extra == 'test'
Requires-Dist: nose-cov (==1.6) ; extra == 'test'
